django_opensearch_dsl_filtering/__init__.py
django_opensearch_dsl_filtering/filters.py
django_opensearch_dsl_filtering-0.1.6.dist-info/licenses/LICENSE
django_opensearch_dsl_filtering-0.1.6.dist-info/METADATA
django_opensearch_dsl_filtering-0.1.6.dist-info/WHEEL
django_opensearch_dsl_filtering-0.1.6.dist-info/top_level.txt
django_opensearch_dsl_filtering-0.1.6.dist-info/RECORD
