Metadata-Version: 2.4
Name: django-opensearch-dsl-filtering
Version: 0.1.6
Summary: A filtering system for Opensearch documents similar to django-filter
Author-email: Ben Atkinson <ben@streamlinedanalytics.co.uk>
License: MIT
Project-URL: Homepage, https://github.com/yourusername/django-opensearch-dsl-filtering
Project-URL: Bug Tracker, https://github.com/yourusername/django-opensearch-dsl-filtering/issues
Keywords: opensearch,django,filter,search
Classifier: Development Status :: 3 - Alpha
Classifier: Intended Audience :: Developers
Classifier: License :: OSI Approved :: MIT License
Classifier: Programming Language :: Python :: 3
Classifier: Programming Language :: Python :: 3.9
Classifier: Programming Language :: Python :: 3.10
Classifier: Programming Language :: Python :: 3.11
Requires-Python: >=3.9
License-File: LICENSE
Requires-Dist: django>=3.2
Requires-Dist: django-opensearch-dsl>=0.5.0
Dynamic: license-file
